selfdiffusion/__init__.py
selfdiffusion/cli.py
selfdiffusion/log.py
selfdiffusion/pipelines/__init__.py
selfdiffusion/sources/__init__.py
selfdiffusion/sources/bing.py
selfdiffusion/transforms/__init__.py
selfdiffusion/transforms/exceptions.py
selfdiffusion/transforms/ml.py
selfdiffusion/transforms/transforms.py
selfdiffusion/transforms/utils.py
selfdiffusion/utils.py
selfdiffusion-0.1.7.dist-info/LICENSE
selfdiffusion-0.1.7.dist-info/METADATA
selfdiffusion-0.1.7.dist-info/WHEEL
selfdiffusion-0.1.7.dist-info/entry_points.txt
selfdiffusion-0.1.7.dist-info/RECORD
