Metadata-Version: 2.1
Name: selfdiffusion
Version: 0.1.7
Summary: Easily create datasets for diffusion models personalization
Home-page: https://github.com/La-Compagnie-Infonuagique/selfdiffusion
Author: Jonathan Pelletier
Author-email: jonathan.pelletier-aafz@thecloudco.ca
Requires-Python: >=3.10,<4.0
Classifier: Programming Language :: Python :: 3
Classifier: Programming Language :: Python :: 3.10
Classifier: Programming Language :: Python :: 3.11
Requires-Dist: click (>=8.0.1,<9.0.0)
Requires-Dist: exceptiongroup ; python_version < "3.11"
Requires-Dist: face-recognition (>=1.3.0,<2.0.0)
Requires-Dist: halo (>=0.0.31,<0.0.32)
Requires-Dist: pillow (>=9.5.0,<10.0.0)
Requires-Dist: ultralytics (>=8.0.66,<9.0.0)
Project-URL: Repository, https://github.com/La-Compagnie-Infonuagique/selfdiffusion
